hashprint/__init__.py
hashprint-1.0.1.dist-info/DESCRIPTION.rst
hashprint-1.0.1.dist-info/METADATA
hashprint-1.0.1.dist-info/RECORD
hashprint-1.0.1.dist-info/WHEEL
hashprint-1.0.1.dist-info/metadata.json
hashprint-1.0.1.dist-info/top_level.txt
