Metadata-Version: 2.0
Name: hashprint
Version: 1.0.1
Summary: Fingerprint Visualization for Public Keys
Home-page: https://github.com/justuswilhelm/hashprint
Author: Justus Perlwitz
Author-email: hello@justus.pw
License: MIT
Platform: UNKNOWN
Classifier: License :: OSI Approved :: MIT License
Classifier: Programming Language :: Python :: 2.7
Classifier: Programming Language :: Python :: 3.3
Classifier: Programming Language :: Python :: 3.6
